filebacked.py
FileBacked-2.1.0.dist-info/METADATA
FileBacked-2.1.0.dist-info/WHEEL
FileBacked-2.1.0.dist-info/top_level.txt
FileBacked-2.1.0.dist-info/RECORD
