Metadata-Version: 2.1
Name: FileBacked
Version: 2.1.0
Summary: Simple file-backed HDF5 storage for Python objects
Home-page: https://github.com/TheBB/FileBacked
Maintainer: Eivind Fonn
Maintainer-email: evfonn@gmail.com
License: UNKNOWN
Platform: UNKNOWN
Requires-Dist: dill
Requires-Dist: numpy
Requires-Dist: scipy
Requires-Dist: typing-inspect
